dlhn/__init__.py
dlhn/dlhn.py
dlhn-0.2.5.dist-info/AUTHORS.rst
dlhn-0.2.5.dist-info/LICENSE
dlhn-0.2.5.dist-info/METADATA
dlhn-0.2.5.dist-info/WHEEL
dlhn-0.2.5.dist-info/entry_points.txt
dlhn-0.2.5.dist-info/top_level.txt
dlhn-0.2.5.dist-info/RECORD
