Metadata-Version: 2.1
Name: dlhn
Version: 0.2.5
Summary: dlhn is a Python CLI script to download my comments and submissions from the Hacker News API and generate a static HTML archive with a Jinja2 template
Home-page: https://github.com/westurner/dlhn
Author: Wes Turner
Author-email: wes@wrd.nu
License: BSD license
Keywords: dlhn
Platform: UNKNOWN
Classifier: Development Status :: 3 - Alpha
Classifier: Intended Audience :: Developers
Classifier: License :: OSI Approved :: BSD License
Classifier: Natural Language :: English
Classifier: Programming Language :: Python :: 2
Classifier: Programming Language :: Python :: 2.7
Classifier: Programming Language :: Python :: 3
Classifier: Programming Language :: Python :: 3.4
Classifier: Programming Language :: Python :: 3.5
Classifier: Programming Language :: Python :: 3.6
Classifier: Programming Language :: Python :: 3.7
Requires-Dist: beautifulsoup4
Requires-Dist: bleach
Requires-Dist: certifi
Requires-Dist: jinja2
Requires-Dist: requests
Requires-Dist: urlobject
Requires-Dist: requests-cache
